quevedo/__init__.py
quevedo/annotation/__init__.py
quevedo/annotation/annotation.py
quevedo/annotation/grapheme.py
quevedo/annotation/logogram.py
quevedo/cli.py
quevedo/darknet/__init__.py
quevedo/darknet/alexnet.cfg
quevedo/darknet/library.py
quevedo/darknet/yolo.cfg
quevedo/dataset.py
quevedo/default_config.toml
quevedo/extract_graphemes.py
quevedo/generate.py
quevedo/inference.py
quevedo/logo.png
quevedo/logo_icon.png
quevedo/migrate.py
quevedo/network/__init__.py
quevedo/network/classify.py
quevedo/network/cli.py
quevedo/network/detect.py
quevedo/network/network.py
quevedo/pipeline.py
quevedo/run_script.py
quevedo/split.py
quevedo/web/__init__.py
quevedo/web/app.py
quevedo/web/static/common.css
quevedo/web/static/common_state.js
quevedo/web/static/edit.css
quevedo/web/static/edit.js
quevedo/web/static/graph.js
quevedo/web/static/i18n/README.md
quevedo/web/static/i18n/en.js
quevedo/web/static/i18n/es.js
quevedo/web/static/lib/htm.js
quevedo/web/static/lib/preact.js
quevedo/web/static/lib/preactHooks.js
quevedo/web/static/list.css
quevedo/web/static/list.js
quevedo/web/static/login.css
quevedo/web/static/login.js
quevedo/web/static/logo.js
quevedo/web/static/page.html
quevedo-1.3.1.dist-info/entry_points.txt
quevedo-1.3.1.dist-info/LICENSE
quevedo-1.3.1.dist-info/WHEEL
quevedo-1.3.1.dist-info/METADATA
quevedo-1.3.1.dist-info/RECORD
